{
  "first_name": "Hassan",
  "last_name": "Mwase",
  "primary_email": null,
  "secondary_email": null,
  "phone": null,
  "city": null,
  "state": null,
  "zip": null,
  "work_authority": null,
  "resume_link": ".Net - TX - Hassan.pdf",
  "raw_resume": "Hassan Mwase\nIT professional with 16+ years of experience as a software developer/solution architect on multiple\nlarge complex projects and production support for a variety of clients including most recent\nexperience developing Web applications. Proficient in analysis, design, development, testing,\nintegration and troubleshooting skills. Result oriented back-end and front-end developer with\nexceptional analytical skills, team oriented, dependable and very flexible. Experience with\nWaterfall and JIRA Agile methodologies.\nTechnical Skills\n Experienced Software development of Web applications using Azure DevOps, Cloud, Git,\nASP.NET Web Application, ASP.NET Web Forms, ASP.NET MVC, C#, .NET\nFramework, Kendo UI , JavaScript, Razor, Angular JS, CSS3, jQuery, bootstrap, Ajax,\ndependency injection, JSON, LINQ, HTML5, Microsoft Visual Studio enterprise 2017,\nActive Server Pages extended files, Eclipse, Test Driven Development(TDD), Selenium\nFramework, Web Services, Postman, Visual Studio code, DevExpress, SQL Server\nManagement Studio.\n Proficient in analysis, design, development, testing, integration and troubleshooting skills.\n Experience with Waterfall and JIRA Agile methodologies.\n Result oriented back-end and front-end developer with exceptional analytical skills, team\noriented, dependable and very flexible.\n Familiarity with REST/ HTML/CSS3.\n Excellent relational database experience using Oracle and SQL Server including writing\nPL/SQL, SQL stored procedures, functions, triggers and views.\n Experience developing using Oracle Database, Oracle Forms, Oracle Reports, SQL*Plus,\nPL/SQL, UNIX, Pro*C.\n Knowledge of Java/J2EE architecture/technologies, WebSphere, Test Driven\nDevelopment TDD and Oracle ADF, ODBC\n Writing unit tests with NUnit and Moq\n Familiar with Regular Expression and Pattern Matching.\n SQL Server – Microsoft SQL Server Management Studio v.18.8, Visual Studio 2017,\nMicrosoft SQL Server Tools for Visual Studio, GraphiViz 2.38 – This is used in the PMEF\nNEDAT and new NSIGHT application as an API for creating bubble visualization images.\nMicrosoft Internet Information Services (IIS) version 10 web server. OleDB API\nUncovered errors in timesheet contracts and Provided guidance in resolving major issues\nfrom past years. Applied fix to application code.\nProfessional Experience\nSecret Security Clearance 11/2020 to 11/2030 May. 2020 – Present\nSenior Software Programmer/Analyst Consultant/Agile developer\nTools: .NET, ASP.NET C#, Web Forms .Net Framework ver.4.6, JavaScript, CSS3, jQuery,\nbootstrap v4.0.0, JSON, LINQ, HTML5, Visual Basic 2017, Microsoft Visual Studio enterprise,\nProudly presented by Hassan Mwase\nHassan Mwase Page 2\nDeveloper, Web Services, Web Forms, Databases: SQL Server and Oracle, Microsoft team TSF\ndevelopment environment\n Develop web applications using C#, ASP.NET and JavaScript.\n As a senior developer, I develop, enhance and Support critical federal Government\nprojects.\n Develop and maintain multiple web applications written in ASP.NET, C#, JavaScript,\nand Web Forms.\n Participate in project meetings with other technical staff, business owners and subject\nmatter experts.\n Troubleshooting and debugging Defects\n Write automated UI test script using ServiceNow ATF Framework.\nFarmers Insurance – USA Sept. 2018 – Aug. 2020\nSenior Programmer/Analyst Consultant/Agile developer\nTools: .NET, ASP.NET C#, MVC, Web Forms .Net Framework ver.4.6, JavaScript, CSS3, jQuery,\nbootstrap v4.0.0, JSON, LINQ, HTML5, Visual Basic 2017, Microsoft Visual Studio enterprise,\nDeveloper, Selenium Framework, Web Services, Web Forms, Databases: SQL Server and DB2 ,\nMicrosoft team TSF development environment\n Develop web applications using C#, Azure DevOps, Git, ASP.NET MVC, JavaScript,\njQuery, Razor MVC.\n Develop and maintain multiple customer web applications written in C#, JavaScript and\nWeb Forms.\n Participate in project meetings with other technical staff, business owners and subject\nmatter experts.\n Troubleshooting and debugging Defects\n Write automated UI test script and fix defects using Selenium Framework.\n Write unit tests with NUnit and Moq\nBoeing Company – USA Feb. 2018 – Sept.2018\nSenior Programmer/Analyst Consultant/Agile developer\nTools: .NET, ASP.NET MVC,C#, MVC, Dependency Injection DI, .Net Framework ver.4.6,\nJavaScript, Razor, Angular JS, CSS3, jQuery, bootstrap, JSON, LINQ, HTML5, Microsoft Visual Studio\nenterprise 2017, PL/SQL, SQL Developer, Databases: Oracle 12C and SQL Server , JIRA Agile, Microsoft\nteam TSF development environment\n Develop server side C# pages, create entities in the relation object mapping to modernize\nBoeing data ERP application using ASP.NET MVC framework.\n Manage Agile task board.\n Design and develop back-end Database stored procedures, functions, triggers and views.\n Code C# interfaces, Classes, view models, API controllers and data services web resources.\n Develop server side XHML5 web pages leveraging angular JS and jQuery.\n Code C# Dependency Injection processes – DI Manager interfaces, DI Manager classes,\nDependency Injection configuration and API Controllers.\nProudly presented by Hassan Mwase\nHassan Mwase Page 3\nCliffs Natural resources - Cleveland, OH July 2016 – Dec. 2017\nSenior Programmer/Analyst Consultant\nTools: .NET, C#, MVC, .Net Framework ver.4.6, JavaScript, AngularJS, CSS, JSON, LINQ, HTML5,\nMicrosoft Visual Studio enterprise 2015, PL/SQL, Postman, SQL Developer, Toad, Databases: Oracle\n12C and SQL Server\n Re-designed the Oracle ERP application and convert oracle forms and reports web application\nusing ASP.NET MVC framework.\n Created Technical specs based on user desired functionality changes.\n Design and develop back-end Database stored procedures, functions, triggers and views.\n Coded C# interfaces, Classes, view models, JavaScript controllers and data services web\nresources.\n Develop front end web content XHML5 web pages leveraging angular JS.\n Code system enhancements, defect fixes and production support.\n Commit and publish finished web application solutions.\n Support project and business users to Create Unit Test, integration, and UAT test scenarios and\nscripts, as well as, performing system and integration testing.\n Design, build and implement client and server side applications as needed, as well as\nsupporting and enhancing custom applications.\nGap Inc. - Columbus, OH July 2015 – Nov. 2015\nSenior Programmer/Analyst Consultant/Agile developer\nTools: Oracle 11G, PL/SQL, SQL Developer, Toad, JDeveloper, Oracle 11G Web logic environment,\nEclipse, JavaScript, Ruby, Eclipse, WebSphere, Tomcat, JIRA Agile development environment.\n Onsite team lead working with product managers and business users to re-design the on-\nline order fulfillment process from batch processing to on-demand and transform oracle\ninterface based application to Web UI.\n Technical lead for on-site/offshore developers and QA.\n Convert legacy forms application to Web UI using JavaScript.\n Coded supporting stored procedures, functions, packages and views.\n Assisted to test conversion of character based SSH screens for RF devices to a stateless\nHTML user interface, update to the tech stack from Oracle Forms to Java6/HTML5,\ndesigned to extend the life of a legacy Warehouse Management System(RWMS)\n Create test cases, run automated system tests and validate output of Ruby automated testing\nfor process online customer orders.\n Support warehouse order processing and shipment message queues(MQ).\n Created Unit Test, integration, and UAT test scenarios and scripts, as well as, performing\nsystem and integration testing.Write integration testing cases.\nCliffs Natural Resources - Cleveland, OH June 2011 – April 2015\nSenior Programmer Consultant\nTools: Oracle 11G, SQL Server, Oracle Forms, Oracle Forms, .NET, C#, MVC,.Net Framework,\nJavaScript, HTML5, Microsoft Visual Studio enterprise 2015, PL/SQL, SQL Developer, Toad\n Support business functions through the development, implementation, and maintenance\nof applications systems.\nProudly presented by Hassan Mwase\nHassan Mwase Page 4\n Responsible for Maintenance and support of Company ERP application, support various\nenterprise applications enhancements and code extensions, build and apply fixes.\n Maintained and coded database objects such as procedures, functions, packages and\ninterface that support ERP applications, ASP.NET MVC, .Net Framework and Object\nBusiness Intelligence Enterprise Edition (OBIEE).\n Coded PL/SQL subprograms that were called by the front-end application written in C#\nand ORM Entity framework.\n Worked with application managers to gather requirements and build solutions based off of\nuser requirements and build enhancements.\n Proactively assess opportunities, risks, challenges for technology and business, define\nscope, plan and schedule of custom enhancements.\n Consistently exceeded project requirements and expectations on-time delivery.\nWalt Disney World - Orlando, FL Feb.2008 – Aug.2010\nLead Senior Programmer/Analyst Consultant\nTools: Oracle 10G, Oracle Retail supply chain, Oracle Retail Merchandizing, Oracle Database, Oracle\nForms, Oracle Forms, PL/SQL, SQL Developer, Toad\n As project Stream lead, managed full lifecycle implementation effort. Engaged client managers to\nreview project plans, timelines and deliverables.\n SME lead Oracle WMS/RMS implementation/integration contractor and client developer team.\n Responsible for analysis, design and final delivery of functioning and technical integrated multiple\nfacility warehouse. Setup and configure environments.\n Designed, wrote code and tested application enhancements, modifications, and interfaces.\nSupported post go-live including system integration stabilization, inventory stock on hand\nimbalance resolution between RWMS13.x and RMS13.x issue resolution and knowledge transfer\nto Disney IT personnel.\nCato Corporation, 8100 Denmark Road, Charlotte, NC Dec. 2007 – Aug. 2008\nProject Lead - Senior Programmer/Analyst Consultant\nLead technical consultant, to upgrade RMS. Plan and recommend most efficient upgrade strategy of all\ncurrent Oracle retail application modules to be web-based.\nTesco Central Europe Prague, Czech Republic Aug.2007 – Oct.2007\nLead Senior Programmer/Analyst Consultant\nLead functional and technical RWMS Project lead consultant, build and deploy Oracle Retail\nWarehouse Management System for both Prevov Fresh DC and Ambient DC. Review foundation and\ntransactional data to ensure successful build, test and implementation process of Slovakian DC in\nPresov\nIBM - Circuit City Richmond, VA Aug.2006 – July 2007\nSenior Analyst Consultant\nTools: RWMS 10.3, UNIX, Pro*C, Oracle Database, SQL*Plus, PL/SQL, Oracle Reports, Oracle Forms,\nOracle, RIB\nLead technical analyst to assist RMS11 implementation and integration. Worked on Purchase\nOrder, Cost and Deals team.\nGAP Inc. – Columbus, OH 2005 – 2006\nSenior Analyst Consultant\nProudly presented by Hassan Mwase\nHassan Mwase Page 5\nTools: RWMS 10.3, UNIX, Pro*C, Oracle Database, SQL*Plus, PL/SQL, Oracle Reports, Oracle Forms,\nOracle, RIB\nDevelopment team lead developer on the WMS system - a highly customized version of Oracle\nRetail WMS.\nRetek/Oracle – Minneapolis, MN 2003 – 2005\nSenior Developer\nTools: RWMS 10.3, UNIX, Pro*C, Oracle Database, SQL*Plus, PL/SQL, Oracle Reports, Oracle Forms,\nOracle, RIB\n Technical lead/supervisor of Retek WMS Developer and customer product support.\n Developed RWMS 10.3/RMS 10.3 and RIB hospital application support interface. On-site DC\noperations support and technical lead for RWMS/RIB at the Navy Exchange Norfolk\nVirginia .\nEducation\nBachelor of Commerce\nUniversity of Calgary, Calgary, Alberta\nComputer Programming\nYork University, Toronto, Ontario\nCertification\nOracle Certified Professional – Certified Oracle DBA\nProudly presented by Hassan Mwase\n",
  "tax_term": null,
  "source_by": null,
  "skills": {
    "programming": [
      "java",
      "javascript",
      "ruby",
      "go",
      "sql",
      "pl/sql",
      "html",
      "css",
      "json",
      "visual basic"
    ],
    "frameworks": [
      "angular",
      "asp.net",
      "jquery",
      "bootstrap",
      "rest",
      "razor",
      "selenium",
      "nunit"
    ],
    "databases": [
      "oracle",
      "sql server",
      "db2"
    ],
    "cloud": [
      "azure",
      "functions",
      "azure devops",
      "batch"
    ],
    "devops": [
      "git",
      "functions",
      "azure devops"
    ],
    "methodologies": [
      "agile",
      "waterfall",
      "devops",
      "tdd"
    ],
    "soft_skills": [
      "analysis"
    ],
    "business_skills": [
      "business intelligence"
    ],
    "data_skills": [
      "batch processing",
      "business intelligence",
      "sql",
      "pl/sql",
      "java"
    ],
    "domain_specific": [
      "insurance",
      "retail",
      "supply chain",
      "education",
      "government",
      "architecture",
      "design",
      "contracts",
      "security"
    ],
    "sdlc": [
      "software development",
      "agile development",
      "integration testing",
      "selenium",
      "postman",
      "issue resolution"
    ]
  },
  "designation": "software developer",
  "experience": "16+"
}