{
  "first_name": "ABDIRAHIM",
  "last_name": "MASLAH",
  "primary_email": "abdirahim008@gmail.com",
  "secondary_email": null,
  "phone": "6143774454",
  "city": "Columbus",
  "state": "OH",
  "zip": null,
  "work_authority": null,
  "resume_link": "ABDIRAHIM MASLAH   - SD - OH.docx",
  "raw_resume": "ABDIRAHIM MASLAH  \n\n\n\n                                           Columbus Ohio\n\nHome: 614-377-4454 Cell: 614-377-4454 abdirahim008@gmail.com \n\nPROFILE\n\nAspiring IT professional actively pursuing an aggressive education to obtain Industry specific certifications.  Highly experienced in customer service protocols and processes.  Comfortable working directly with the customer/client to resolve their issues.  Able to de-escalate problematic situations whether face-to-face or via phone.  Called upon to take the lead in multiple situations to train and mentor peers.  \n\nEDUCATION\n\nMy Computer career, Columbus, Ohio \t\t\t\t\t\tGraduated June 2016\n\nInformation Technology system Administration \n\nCurrent Certification: MTA Network fundamentals, CompTIA Network+, CompTIA A+, CompTIA Server Plus and MTA Windows OS. \n\nCertification in progress: Mobility + CompTIA, CNNA, MCTS (Window 7), MCTS (Window server Enterprise Administrator), CompTIA Security+, and CCNP \n\nTECHNICAL HIGHLIGHTS\n\nInformation system fundamentals         \n\nInstalling, maintaining, and troubleshooting LAN Network\n\nInstalling, maintaining, and troubleshooting Window Vista, XP, and Window 7\n\nInstall and troubleshoot network cables. ( Cat 6 3,5and )\n\nServer installation and management \n\n\n\nImplement router and switch security techniques \n\nTroubleshoot network issues \n\nTrained in HTML and CSS language\n\nKeyboarding 50WPM\n\nMicrosoft Office \n\nInstall physical and virtual servers\n\nActive directory \n\nCoca-Cola    \n\nHelp Desk Analyst\n\nColumbus, Ohio\n\n                                                   6/8/2017 to present \n\n\n\n\n\n\n\nResponds to customer technical problems/issues related to various OEM hardware  and software platforms\n\nAssists customers by diagnosing problems and providing resolutions for technical issues\n\nUses troubleshooting techniques and tools to identify products that are defective and follow guidelines in issuing service calls/contacts\n\nUtilized Service Now to open, document, and resolve helpdesk tickets in accordance procedures.\n\n Performs PC, laptop, and printer moves and installations. \n\n Advises/educates customers within procedural guidelines to ensure a complete solution to their technical or service questions\n\nUtilized ServiceNow ticketing system.\n\n\n\nJPMorgan Chase    \n\nHelp Desk Analyst/ hardware refresh\n\nWesterville, Ohio                                                                                      \n\n                                                   4/8/2015 to 5/25/2017\n\n\n\n\n\n\n\nproviding phone support for Windows 7 & 8 desktop environment including Active Directory (AD), within a Retail Financial Services environment\n\nIn-depth knowledge of several technology disciplines including PC, Server, and Network infrastructure as well as Mobile Messaging/Communication software and hardware such as smart phones, broadband cards and other wireless technologies\n\nUtilized ServiceNow ticketing system.\n\nStrong customer service skills via phone, instant message (IM), along with strong documentation skills\n\nConfigure and troubleshoot UPS’s and Micro pods. \n\n\n\nField Nation \t\t\t\t\t\t\t\t          5/25/2015 to present \n\nFreelance contractor/ Help Desk Analyst\n\nColumbus, Ohio \n\nInstalling CAT 5 and CAT 6 cables, Testing and terminating cables, Patching panels, \n\nSolving issues related to cables and networks\n\nTerminate phone jacks\n\nDemonstrate proper procedures, encourage safe use, document in ServiceNow.\n\nWorked with TCP/IP, assigning/reassigning IP addresses and with Novell Servers, Windows NT and DNS.",
  "tax_term": null,
  "source_by": null,
  "skills": {
    "programming": [
      "html",
      "css"
    ],
    "methodologies": [
      "safe",
      "xp"
    ],
    "soft_skills": [
      "documentation"
    ],
    "domain_specific": [
      "retail",
      "education",
      "infrastructure",
      "customer service",
      "security"
    ]
  },
  "designation": "Network Technician",
  "experience": null
}