{
  "first_name": "ABHISHEK",
  "last_name": "Heera",
  "primary_email": "abhishek.heera11@gmail.com",
  "secondary_email": null,
  "phone": "7814864747",
  "city": "MD",
  "state": "VA",
  "zip": null,
  "work_authority": null,
  "resume_link": "Abhishek-devops-mig.docx",
  "raw_resume": "ABHISHEK Heera\n\nDevOps/Migration Engineer\n\nPhone: (781)-486-4747 | Email: abhishek.heera11@gmail.com\n\n\n\nPROFESSIONAL SUMMARY\n\nAround 7 years of experience in Cloud Infrastructure and DevOps experience building CI/CD pipelines and automation.\n\nHands on experience with configuration management tools such as Chef, Ansible. Version control using GIT, SVN. Containerization using Docker and Kubernetes, continuous integration using Jenkins, Bamboo and worked on build tools like ANT and Maven.\n\nExperience in Continuous Integration and deployment using various like Jenkins, Hudson, Bamboo, Chef, and Puppet.\n\nExpert in Jira Atlassian admin. Have worked extensively with Jira plugins like Tempo, WBS, Jira Automation, Docker.\n\nConfigures and administers Jira Software, Jira Core and/or Jira Service Desk, and related products such as apps.\n\nExperience in working on AWS and its services like AWS IAM, VPC, EC2, ECS, EBS, RDS, S3, Lambda, ELB, Auto Scaling, Route 53, Cloud Front, Cloud Watch, Cloud Trail, SQS, and SNS.\n\nExperienced in Cloud automation using AWS Cloud Formation templates to create custom sized VPC, subnets, NAT, EC2 instances, ELB and Security groups.\n\nManages global settings including users and groups, roles, global permissions, and schemes.\n\nCreates projects, sets up project permissions, and assigns Jira project administrators.\n\nExpertise in all areas of SCM processes, including version, build and issue management, build and release management. \n\nExpert in deploying the code through web application servers like WebSphere/Web Logic/ Apache Tomcat/JBOSS \n\nGood experience in middleware services JDBC, SSL certificates in WebLogic.\n\nExpertise in Deploying and troubleshooting the J2EE Applications (WAR & EAR) in JBOSS Application Server\n\nExperience with maintaining the 24x7 production environments on public Cloud environments (AWS, Azure) and       on prem.\n\nExtensive experience in setting up the CI/CD pipelines using Jenkins, Maven, Nexus, GitHub, CHEF, Terraform and AWS.\n\nDeveloped Python scripts for software build conduct and management support.\n\nExtensive experience using MAVEN and ANT as build tools for the building of deployable artifacts (jar, war, ear) from raw source code.\n\nExtensively worked on Jenkins for continuous integration and End-to-End automation for all build and deployments.\n\nExperience working on several Docker components like Docker Engine, Hub, Machine, creating Docker images, Compose, Docker Registry and handling multiple images primarily for middleware installations and domain configurations.\n\nBuilding/Maintaining Docker container clusters managed by Kubernetes. \n\nWorking on On-Premises and AWS platforms utilizing DevOps/Agile operational processes.\n\nExperience in designing, configuring and deploying solutions on Microsoft Azure using ARM Templates, AZURE PowerShell Module and, Azure CLI focusing on high-availability and auto-scaling.",
  "tax_term": null,
  "source_by": null,
  "skills": {
    "programming": [
      "python",
      "powershell",
      "arm",
      "ant",
      "puppet",
      "chef"
    ],
    "frameworks": [
      "terraform",
      "ansible",
      "chef",
      "puppet"
    ],
    "cloud": [
      "aws",
      "azure",
      "s3",
      "ec2",
      "lambda",
      "rds",
      "vpc",
      "iam",
      "kubernetes",
      "docker",
      "terraform",
      "ansible",
      "jenkins"
    ],
    "devops": [
      "docker",
      "kubernetes",
      "jenkins",
      "ansible",
      "terraform",
      "puppet",
      "chef",
      "bamboo",
      "git",
      "svn",
      "github",
      "vpc",
      "iam",
      "nexus",
      "tempo"
    ],
    "methodologies": [
      "agile",
      "devops",
      "ci/cd",
      "nexus",
      "continuous integration"
    ],
    "data_skills": [
      "python"
    ],
    "domain_specific": [
      "infrastructure",
      "security"
    ],
    "sdlc": [
      "version control",
      "continuous integration",
      "configuration management"
    ]
  },
  "designation": "Cloud Infrastructure",
  "experience": "7"
}