{
  "first_name": "Adam",
  "last_name": "Turner",
  "primary_email": "Adam.turner.jobs1@gmail.com",
  "secondary_email": null,
  "phone": "7176545847",
  "city": "Lemoyne",
  "state": "PA",
  "zip": "17043",
  "work_authority": null,
  "resume_link": "Adam Turner - .Net - VA.docx",
  "raw_resume": "344 Plum St. Lemoyne, PA 17043\n\nCell Phone: 717-654-5847\n\nAdam.turner.jobs1@gmail.com  \n\nAdam Turner\n\nProfessional Summary\n\nSenior .net enterprise engineer with over 17 years of industry experience\n\nExperienced Lead Programmer with end-to-end project lifecycle (SDLC) \n\nPrimary expertise in full stack multi-tier architecture.\n\nExperienced Trainer\n\nComptia Security+ Certified\n\nExperience\n\n10/16 – Present     V Group Inc @ SERS     Harrisburg, PA\n\nSenior .Net Developer (6-12 month contract) 2 ½ years later\n\nComplete redesign of public facing site https://employers.sers.pa.gov \n\nDeveloped ASP.net MVC Ad hoc app (AGC) to work with 3rd party CMS product (Process360)\n\nDeveloped two associated ASP.net Web Forms Applications\n\nOAP – Public facing site to apply for agency specific jobs.\n\nOAPA – Intranet site to administer the application\n\nDeveloped JNET WCF SSL Service. Shared code with 2 other agencies and assisted them with setup.\n\nNew development and maintenance of .Net VTA’s\n\nDeveloped a WinForms application and .dll to encrypt-decrypt sensitive data i.e. connection strings (AES)\n\nASP.net Web Forms & SOAP Web Services (ASMX & WCF) Maintenance and Bugs Fixes for intranet app’s (DAWPM & CMS)\n\nCurrently working with 2 teams for SERIS 2.0 migration as lead .net developer.\n\nTechnologies used: .Net Framework 2.0/4.0, Visual Studio 2015, VB.net & C#, JavaScript/JQuery TFS 2015 Web & Intergrated, T-SQL/Oracle, XPath, LINQ, AJAX, HTML, CSS, Bootstrap\n\n\n\n4/16 – 8/16      Accenture/Navy Depot      Mechanicsburg, PA\n\n.Net SME/Trainer (6-12 month contract) \n\nLead Trainer of a 4 week (160 hours) of training class of 9 experienced developers on the following topics in .Net (OOP Concepts and UML, Software Analysis Design & Build, SOLID Principles, Software Development Environment & Tools, Programming Language: C#, Error Handling/Assertions, Reuse: Procedural Classes & Objects, Programming Inheritance, Programming Polymorphism, Programming Collections, Programming Exception Handling, OOP Paradigm, Unit Testing, Assembly and Production Testing, Database Input/Output, Database Overview, Getting Started with LINQ, Getting Started with Entity Framework, Database Connectivity, Elements of Enterprise Architecture, Enterprise Architecture Patterns, Web Based Programming, XML & XSLT, MVC, Securing Applications, Working with MVC Models, Designing ASP.NET MVC Application Architecture, Coding Fundamentals for C#, Define, Revise, & Prepare Unit Test, And a few other smaller topics\n\nFollowing training, I'm provided over the shoulder support for the entire depot regarding .net technologies. (85+ developers)",
  "tax_term": "CONTRACT",
  "source_by": null,
  "skills": {
    "programming": [
      "javascript",
      "sql",
      "t-sql",
      "html",
      "css",
      "xml",
      "assembly",
      "xslt"
    ],
    "frameworks": [
      "asp.net",
      "jquery",
      "bootstrap",
      "soap"
    ],
    "databases": [
      "oracle"
    ],
    "soft_skills": [
      "analysis",
      "training"
    ],
    "data_skills": [
      "sql",
      "t-sql"
    ],
    "domain_specific": [
      "architecture",
      "design",
      "security"
    ],
    "sdlc": [
      "enterprise architecture",
      "software development",
      "unit testing"
    ]
  },
  "designation": "Senior Software Developer",
  "experience": "17"
}